ipdab/__init__.py
ipdab/debugger.py
ipdab/server.py
ipdab-25.8.4.dist-info/licenses/LICENSE
ipdab-25.8.4.dist-info/WHEEL
ipdab-25.8.4.dist-info/METADATA
ipdab-25.8.4.dist-info/RECORD
