Metadata-Version: 2.4
Name: ipdab
Version: 25.8.4
Summary: The Debug Adapter Protocol (DAP) implementation for the ipdb debugger.
Keywords: debugger,dap,ipdb,debug-adapter-protocol,python
Author: Martin van der Schans
Requires-Python: >=3.9
License-File: LICENSE
Requires-Dist: ipython<9.1
Project-URL: repository, https://github.com/mvds314/ipdab
